{
  "bugs": [
    {
      "id": 1,
      "name": "Server communication failure",
      "isClosed": false,
      "createdAt": "2015-07-31T18:30:00.000Z"
    },
    {
      "id": 2,
      "name": "Stack overflow error",
      "isClosed": false,
      "createdAt": "2015-06-28T18:30:00.000Z"
    },
    {
      "id": 3,
      "name": "Object reference not found",
      "isClosed": false,
      "createdAt": "2015-06-25T18:30:00.000Z"
    },
    {
      "id": 4,
      "name": "User authentication failure",
      "isClosed": false,
      "createdAt": "2015-06-20T18:30:00.000Z"
    },
    {
      "name": "File system access compromised",
      "isClosed": false,
      "createdAt": "2015-05-31T18:30:00.000Z",
      "id": 5
    }
  ]
}
